<?xml version="1.0" encoding="utf-8"?><text id="2577" parent="583" name="1004809"><tags><tag>url:http://pe3yc.livejournal.com/1004809.html</tag></tags><paragraphs><paragraph id="22320"><sentence id="66280"><source>А вот в Шереметьево F бесплатный вайфай есть, даже от нескольких операторов.</source><tokens><token id="1206647" text="А"><tfr rev_id="2833417" t="А"><v><l id="51" t="а"><g v="CONJ"></g></l></v><v><l id="52" t="а"><g v="INTJ"></g></l></v><v><l id="53" t="а"><g v="PRCL"></g></l></v></tfr></token><token id="1206648" text="вот"><tfr rev_id="2833418" t="вот"><v><l id="52157" t="вот"><g v="PRCL"></g></l></v></tfr></token><token id="1206649" text="в"><tfr rev_id="2833419" t="в"><v><l id="37409" t="в"><g v="PREP"></g></l></v></tfr></token><token id="1206650" text="Шереметьево"><tfr rev_id="4303569" t="Шереметьево"><v><l id="379215" t="шереметьево"><g v="NOUN"></g><g v="inan"></g><g v="neut"></g><g v="Sgtm"></g><g v="Geox"></g><g v="sing"></g><g v="loct"></g><g v="Infr"></g></l></v></tfr></token><token id="1206651" text="F"><tfr rev_id="2833421" t="F"><v><l id="0" t="F"><g v="LATN"></g></l></v></tfr></token><token id="1206652" text="бесплатный"><tfr rev_id="2833422" t="бесплатный"><v><l id="28393" t="бесплатный"><g v="ADJF"></g><g v="Qual"></g><g v="masc"></g><g v="sing"></g><g v="nomn"></g></l></v><v><l id="28393" t="бесплатный"><g v="ADJF"></g><g v="Qual"></g><g v="inan"></g><g v="masc"></g><g v="sing"></g><g v="accs"></g></l></v></tfr></token><token id="1206653" text="вайфай"><tfr rev_id="2833423" t="вайфай"><v><l id="0" t="вайфай"><g v="UNKN"></g></l></v></tfr></token><token id="1206654" text="есть"><tfr rev_id="4394421" t="есть"><v><l id="37265" t="есть"><g v="VERB"></g><g v="impf"></g><g v="intr"></g><g v="sing"></g><g v="3per"></g><g v="pres"></g><g v="indc"></g></l></v><v><l id="37265" t="есть"><g v="VERB"></g><g v="impf"></g><g v="intr"></g><g v="plur"></g><g v="3per"></g><g v="pres"></g><g v="indc"></g></l></v></tfr></token><token id="1206655" text=","><tfr rev_id="2833425" t=","><v><l id="0" t=","><g v="PNCT"></g></l></v></tfr></token><token id="1206656" text="даже"><tfr rev_id="4079597" t="даже"><v><l id="77849" t="даже"><g v="PRCL"></g></l></v></tfr></token><token id="1206657" text="от"><tfr rev_id="2833427" t="от"><v><l id="211644" t="от"><g v="PREP"></g></l></v></tfr></token><token id="1206658" text="нескольких"><tfr rev_id="3504477" t="нескольких"><v><l id="188126" t="несколько"><g v="NUMR"></g><g v="gent"></g></l></v></tfr></token><token id="1206659" text="операторов"><tfr rev_id="4218749" t="операторов"><v><l id="206946" t="оператор"><g v="NOUN"></g><g v="anim"></g><g v="masc"></g><g v="plur"></g><g v="gent"></g></l></v></tfr></token><token id="1206660" text="."><tfr rev_id="2833430" t="."><v><l id="0" t="."><g v="PNCT"></g></l></v></tfr></token></tokens></sentence><sentence id="66281"><source>Но Мегафон и Билайн по-прежнему хотят за аэропортовый вайфай денег.</source><tokens><token id="1206661" text="Но"><tfr rev_id="2833431" t="Но"><v><l id="191429" t="но"><g v="CONJ"></g></l></v><v><l id="191430" t="но"><g v="INTJ"></g></l></v></tfr></token><token id="1206662" text="Мегафон"><tfr rev_id="3944437" t="Мегафон"><v><l id="156925" t="мегафон"><g v="NOUN"></g><g v="inan"></g><g v="masc"></g><g v="sing"></g><g v="nomn"></g></l></v></tfr></token><token id="1206663" text="и"><tfr rev_id="2833433" t="и"><v><l id="116949" t="и"><g v="CONJ"></g></l></v><v><l id="116950" t="и"><g v="INTJ"></g></l></v></tfr></token><token id="1206664" text="Билайн"><tfr rev_id="2833434" t="Билайн"><v><l id="29557" t="билайн"><g v="NOUN"></g><g v="inan"></g><g v="masc"></g><g v="Sgtm"></g><g v="Orgn"></g><g v="sing"></g><g v="nomn"></g></l></v><v><l id="29557" t="билайн"><g v="NOUN"></g><g v="inan"></g><g v="masc"></g><g v="Sgtm"></g><g v="Orgn"></g><g v="sing"></g><g v="accs"></g></l></v></tfr></token><token id="1206665" text="по-прежнему"><tfr rev_id="2833435" t="по-прежнему"><v><l id="241307" t="по-прежнему"><g v="ADVB"></g></l></v></tfr></token><token id="1206666" text="хотят"><tfr rev_id="2833436" t="хотят"><v><l id="371713" t="хочу"><g v="VERB"></g><g v="impf"></g><g v="tran"></g><g v="plur"></g><g v="3per"></g><g v="pres"></g><g v="indc"></g></l></v></tfr></token><token id="1206667" text="за"><tfr rev_id="2833437" t="за"><v><l id="98043" t="за"><g v="PREP"></g></l></v></tfr></token><token id="1206668" text="аэропортовый"><tfr rev_id="2833438" t="аэропортовый"><v><l id="21367" t="аэропортовый"><g v="ADJF"></g><g v="masc"></g><g v="sing"></g><g v="nomn"></g></l></v><v><l id="21367" t="аэропортовый"><g v="ADJF"></g><g v="inan"></g><g v="masc"></g><g v="sing"></g><g v="accs"></g></l></v></tfr></token><token id="1206669" text="вайфай"><tfr rev_id="2833439" t="вайфай"><v><l id="0" t="вайфай"><g v="UNKN"></g></l></v></tfr></token><token id="1206670" text="денег"><tfr rev_id="4325488" t="денег"><v><l id="81429" t="деньги"><g v="NOUN"></g><g v="inan"></g><g v="femn"></g><g v="plur"></g><g v="gent"></g></l></v></tfr></token><token id="1206671" text="."><tfr rev_id="2833441" t="."><v><l id="0" t="."><g v="PNCT"></g></l></v></tfr></token></tokens></sentence><sentence id="66282"><source>Непонятно только, кто же им в такой ситуации будет платить.</source><tokens><token id="1206672" text="Непонятно"><tfr rev_id="2833442" t="Непонятно"><v><l id="186146" t="непонятно"><g v="ADVB"></g><g v="Prdx"></g></l></v><v><l id="186150" t="непонятен"><g v="ADJS"></g><g v="Qual"></g><g v="neut"></g><g v="sing"></g></l></v></tfr></token><token id="1206673" text="только"><tfr rev_id="3784961" t="только"><v><l id="347395" t="только"><g v="CONJ"></g></l></v><v><l id="347396" t="только"><g v="PRCL"></g></l></v><v><l id="390053" t="только"><g v="ADVB"></g></l></v></tfr></token><token id="1206674" text=","><tfr rev_id="2833444" t=","><v><l id="0" t=","><g v="PNCT"></g></l></v></tfr></token><token id="1206675" text="кто"><tfr rev_id="2833445" t="кто"><v><l id="144216" t="кто"><g v="NPRO"></g><g v="masc"></g><g v="sing"></g><g v="nomn"></g></l></v></tfr></token><token id="1206676" text="же"><tfr rev_id="2833446" t="же"><v><l id="96208" t="же"><g v="CONJ"></g></l></v><v><l id="96209" t="же"><g v="PRCL"></g></l></v></tfr></token><token id="1206677" text="им"><tfr rev_id="4530624" t="им"><v><l id="206619" t="они"><g v="NPRO"></g><g v="3per"></g><g v="Anph"></g><g v="plur"></g><g v="datv"></g></l></v></tfr></token><token id="1206678" text="в"><tfr rev_id="2833448" t="в"><v><l id="37409" t="в"><g v="PREP"></g></l></v></tfr></token><token id="1206679" text="такой"><tfr rev_id="4380510" t="такой"><v><l id="342491" t="такой"><g v="ADJF"></g><g v="Apro"></g><g v="femn"></g><g v="sing"></g><g v="loct"></g></l></v></tfr></token><token id="1206680" text="ситуации"><tfr rev_id="4313839" t="ситуации"><v><l id="321441" t="ситуация"><g v="NOUN"></g><g v="inan"></g><g v="femn"></g><g v="sing"></g><g v="loct"></g></l></v></tfr></token><token id="1206681" text="будет"><tfr rev_id="2833451" t="будет"><v><l id="37265" t="есть"><g v="VERB"></g><g v="impf"></g><g v="intr"></g><g v="sing"></g><g v="3per"></g><g v="futr"></g><g v="indc"></g></l></v></tfr></token><token id="1206682" text="платить"><tfr rev_id="2833452" t="платить"><v><l id="240012" t="платить"><g v="INFN"></g><g v="impf"></g><g v="tran"></g></l></v></tfr></token><token id="1206683" text="."><tfr rev_id="2833453" t="."><v><l id="0" t="."><g v="PNCT"></g></l></v></tfr></token></tokens></sentence></paragraph><paragraph id="22321"><sentence id="66283"><source>Вайфай неплохой, даже SIP работает нормально, без лагов.</source><tokens><token id="1206684" text="Вайфай"><tfr rev_id="2833454" t="Вайфай"><v><l id="0" t="вайфай"><g v="UNKN"></g></l></v></tfr></token><token id="1206685" text="неплохой"><tfr rev_id="3693118" t="неплохой"><v><l id="185803" t="неплохой"><g v="ADJF"></g><g v="masc"></g><g v="sing"></g><g v="nomn"></g></l></v><v><l id="185803" t="неплохой"><g v="ADJF"></g><g v="inan"></g><g v="masc"></g><g v="sing"></g><g v="accs"></g></l></v></tfr></token><token id="1206686" text=","><tfr rev_id="2833456" t=","><v><l id="0" t=","><g v="PNCT"></g></l></v></tfr></token><token id="1206687" text="даже"><tfr rev_id="4079598" t="даже"><v><l id="77849" t="даже"><g v="PRCL"></g></l></v></tfr></token><token id="1206688" text="SIP"><tfr rev_id="2833458" t="SIP"><v><l id="0" t="SIP"><g v="LATN"></g></l></v></tfr></token><token id="1206689" text="работает"><tfr rev_id="2833459" t="работает"><v><l id="290502" t="работаю"><g v="VERB"></g><g v="impf"></g><g v="intr"></g><g v="sing"></g><g v="3per"></g><g v="pres"></g><g v="indc"></g></l></v></tfr></token><token id="1206690" text="нормально"><tfr rev_id="2833460" t="нормально"><v><l id="192216" t="нормально"><g v="ADVB"></g></l></v><v><l id="192219" t="нормален"><g v="ADJS"></g><g v="Qual"></g><g v="neut"></g><g v="sing"></g></l></v></tfr></token><token id="1206691" text=","><tfr rev_id="2833461" t=","><v><l id="0" t=","><g v="PNCT"></g></l></v></tfr></token><token id="1206692" text="без"><tfr rev_id="2833462" t="без"><v><l id="25481" t="без"><g v="PREP"></g></l></v></tfr></token><token id="1206693" text="лагов"><tfr rev_id="2833463" t="лагов"><v><l id="146257" t="лаг"><g v="NOUN"></g><g v="inan"></g><g v="masc"></g><g v="plur"></g><g v="gent"></g></l></v></tfr></token><token id="1206694" text="."><tfr rev_id="2833464" t="."><v><l id="0" t="."><g v="PNCT"></g></l></v></tfr></token></tokens></sentence></paragraph></paragraphs></text>